idatasets/__init__.py
idatasets/conftest.py
idatasets/datasets/__init__.py
idatasets/datasets/basic_loaders.py
idatasets/datasets/devdas.py
idatasets/datasets/devdas.txt
idatasets/datasets/monolingual.py
idatasets/datasets/util.py
idatasets/datasets/wikipedia.py
idatasets/vendor/WikiExtractor.py
idatasets/vendor/__init__.py
indic_nlp_datasets-0.1.2.dist-info/LICENSE
indic_nlp_datasets-0.1.2.dist-info/METADATA
indic_nlp_datasets-0.1.2.dist-info/WHEEL
indic_nlp_datasets-0.1.2.dist-info/entry_points.txt
indic_nlp_datasets-0.1.2.dist-info/top_level.txt
indic_nlp_datasets-0.1.2.dist-info/zip-safe
indic_nlp_datasets-0.1.2.dist-info/RECORD
