Metadata-Version: 2.1
Name: indic-nlp-datasets
Version: 0.1.2
Summary: Indic NLP dataset loader
Home-page: https://github.com/rahul1990gupta/indic-nlp-datasets
Author: Rahul Gupta
Author-email: rahul1990gupta@gmail.com
License: MIT
Platform: UNKNOWN
Classifier: License :: OSI Approved :: MIT License
Classifier: Programming Language :: Python :: 3
Requires-Python: >=3.6
Requires-Dist: tqdm
